{
  "id": "commons-118003983-short-toed-treecreeper-certhia-brachydactyla-bra",
  "scientificName": "Certhia brachydactyla",
  "commonName": "Short-toed treecreeper",
  "commonsPageId": 118003983,
  "commonsTitle": "File:Short-toed treecreeper (Certhia brachydactyla brachydactyla).jpg",
  "filePageUrl": "https://commons.wikimedia.org/wiki/File%3AShort-toed_treecreeper_(Certhia_brachydactyla_brachydactyla).jpg",
  "sourceUrl": "https://upload.wikimedia.org/wikipedia/commons/7/7e/Short-toed_treecreeper_%28Certhia_brachydactyla_brachydactyla%29.jpg",
  "downloadedUrl": "https://upload.wikimedia.org/wikipedia/commons/thumb/7/7e/Short-toed_treecreeper_%28Certhia_brachydactyla_brachydactyla%29.jpg/960px-Short-toed_treecreeper_%28Certhia_brachydactyla_brachydactyla%29.jpg",
  "licenseShortName": "CC BY-SA 4.0",
  "licenseUrl": "https://creativecommons.org/licenses/by-sa/4.0",
  "usageTerms": "Creative Commons Attribution-Share Alike 4.0",
  "artist": "Charles J. Sharp",
  "credit": "Own work, from Sharp Photography, sharpphotography.co.uk",
  "originalWidth": 1455,
  "originalHeight": 2184,
  "processedWidth": 640,
  "processedHeight": 960,
  "processedBytes": 88476
}
