{
  "id": "commons-122564547-house-martins-delichon-urbicum-meridionale-at-ne",
  "scientificName": "Delichon urbicum",
  "commonName": "Common house martin",
  "commonsPageId": 122564547,
  "commonsTitle": "File:House martins (Delichon urbicum meridionale) at nest.jpg",
  "filePageUrl": "https://commons.wikimedia.org/wiki/File%3AHouse_martins_(Delichon_urbicum_meridionale)_at_nest.jpg",
  "sourceUrl": "https://upload.wikimedia.org/wikipedia/commons/a/ad/House_martins_%28Delichon_urbicum_meridionale%29_at_nest.jpg",
  "downloadedUrl": "https://upload.wikimedia.org/wikipedia/commons/thumb/a/ad/House_martins_%28Delichon_urbicum_meridionale%29_at_nest.jpg/960px-House_martins_%28Delichon_urbicum_meridionale%29_at_nest.jpg",
  "licenseShortName": "CC BY-SA 4.0",
  "licenseUrl": "https://creativecommons.org/licenses/by-sa/4.0",
  "usageTerms": "Creative Commons Attribution-Share Alike 4.0",
  "artist": "Charles J. Sharp",
  "credit": "Own work, from Sharp Photography, sharpphotography.co.uk",
  "originalWidth": 2830,
  "originalHeight": 1887,
  "processedWidth": 640,
  "processedHeight": 427,
  "processedBytes": 99260
}
